.gitignore
LICENSE
README.md
bitbucket-pipelines.yml
conftest.py
pytest.ini
requirements.txt
setup.py
ec2userkeyd/__init__.py
ec2userkeyd/cli.py
ec2userkeyd/clients.py
ec2userkeyd/config.py
ec2userkeyd/iam_policy.py
ec2userkeyd/proxy.py
ec2userkeyd/utils.py
ec2userkeyd.egg-info/PKG-INFO
ec2userkeyd.egg-info/SOURCES.txt
ec2userkeyd.egg-info/dependency_links.txt
ec2userkeyd.egg-info/entry_points.txt
ec2userkeyd.egg-info/requires.txt
ec2userkeyd.egg-info/top_level.txt
ec2userkeyd/methods/__init__.py
ec2userkeyd/methods/base.py
ec2userkeyd/methods/create_user_role.py
ec2userkeyd/methods/instance_role.py
ec2userkeyd/methods/restricted_instance_role.py
ec2userkeyd/methods/user_role.py
tests/__init__.py
tests/test_cli.py
tests/test_clients.py
tests/test_config.py
tests/test_iam_policy.py
tests/test_integration.py
tests/test_proxy.py
tests/test_utils.py
tests/methods/test_base.py
tests/methods/test_create_user_role.py
tests/methods/test_instance_role.py
tests/methods/test_restricted_instance_role.py
tests/methods/test_user_role.py