Metadata-Version: 2.1
Name: ec2userkeyd
Version: 0.5.0
Summary: EC2 user credential daemon
Home-page: UNKNOWN
Author: Karl Gutwin
Author-email: karl@bioteam.net
License: UNKNOWN
Platform: UNKNOWN
Classifier: Programming Language :: Python :: 3
Classifier: Operating System :: POSIX :: Linux
Requires-Python: >=3.6
